{
  "id": "0004tCVR",
  "projectName": "Kalyx",
  "link": "https://www.kalyx.io",
  "twitter": "https://twitter.com/dionysuspool",
  "category": "DEFI",
  "subCategory": "UNKNOWN",
  "description": {
    "short": "Kalyx provides a service of decentralized contracts for future difference (dCFDs), operated on the Cardano Blockchain."
  },
  "scripts": [
    {
      "id": "KHfQPsaa",
      "name": "Unknown",
      "purpose": "SPEND",
      "type": "PLUTUS",
      "scriptHash": "40f8745708ac503839d7fb4f9095c1ea6b1de0036ab89a598b09f29b",
      "fullScriptHash": "7140f8745708ac503839d7fb4f9095c1ea6b1de0036ab89a598b09f29b",
      "plutusVersion": 2
    },
    {
      "id": "KHfQPsaa",
      "name": "Unknown",
      "purpose": "MINT",
      "type": "PLUTUS",
      "scriptHash": "40f8745708ac503839d7fb4f9095c1ea6b1de0036ab89a598b09f29b",
      "fullScriptHash": "7140f8745708ac503839d7fb4f9095c1ea6b1de0036ab89a598b09f29b",
      "plutusVersion": 2
    }
  ]
}